README.md
setup.py
that_is_me_on_github/__init__.py
that_is_me_on_github/config.py
that_is_me_on_github/main.py
that_is_me_on_github.egg-info/PKG-INFO
that_is_me_on_github.egg-info/SOURCES.txt
that_is_me_on_github.egg-info/dependency_links.txt
that_is_me_on_github.egg-info/entry_points.txt
that_is_me_on_github.egg-info/requires.txt
that_is_me_on_github.egg-info/top_level.txt
that_is_me_on_github/lib/__init__.py
that_is_me_on_github/lib/render.py
that_is_me_on_github/lib/utils.py