Metadata-Version: 2.1
Name: that-is-me-on-github
Version: 0.0.3
Summary: A Python cli for collecting and showing your github contributions as simple and detailed as possible.
Home-page: https://github.com/hustclf/that_is_me_on_github
Author: hustclf
Author-email: hustclf@gmail.com
License: UNKNOWN
Platform: UNKNOWN
Classifier: Programming Language :: Python :: 3
Classifier: License :: OSI Approved :: MIT License
Classifier: Operating System :: OS Independent
